{
  "items": [
    {
      "code": "04VA511",
      "description": "PREMIUM BLUE 7800 15W40 | 3,785L",
      "price": 28952,
      "quantity": 1,
      "discount": 10,
      "fixedPrice": null
    },
    {
      "code": "04VA502",
      "description": "PREMIUM BLUE 7700 15W40 | 3,785L",
      "price": 28589,
      "quantity": 1,
      "discount": 10,
      "fixedPrice": null
    },
    {
      "code": "01VA173",
      "description": "ALL FLEET MAX 15W40 SF CD | 205L",
      "price": 699000,
      "quantity": 1,
      "discount": null,
      "fixedPrice": null
    },
    {
      "code": "01VA509",
      "description": "PREMIUM BLUE 7800 15W40 CI4 SL MB 8.3 | 205L",
      "price": 950000,
      "quantity": 1,
      "discount": null,
      "fixedPrice": null
    },
    {
      "code": "01VA500",
      "description": "PREMIUM BLUE 7700 15W40 CH4 SJ MB 228.1 | 205L",
      "price": 875000,
      "quantity": 1,
      "discount": null,
      "fixedPrice": null
    },
    {
      "code": "PE/10W40/4",
      "description": "PUMA EXTRA GD 10W40 | 4 X 4L",
      "price": 27647,
      "quantity": 1,
      "discount": 10,
      "fixedPrice": null
    }
  ],
  "mode": "presupuesto",
  "listId": "0"
}